prioQbyrobi/__init__.py
prioQbyrobi-2.0.6.dist-info/LICENSE
prioQbyrobi-2.0.6.dist-info/METADATA
prioQbyrobi-2.0.6.dist-info/WHEEL
prioQbyrobi-2.0.6.dist-info/top_level.txt
prioQbyrobi-2.0.6.dist-info/RECORD
