Metadata-Version: 2.1
Name: prioQbyrobi
Version: 2.0.6
Summary: A package for priority queue to make A* Search
Home-page: https://github.com/Mrrobi/prioQ
Author: Md Robiuddin
Author-email: mrrobi040@gmail.com
License: UNKNOWN
Platform: UNKNOWN
Classifier: Programming Language :: Python :: 3
Classifier: License :: OSI Approved :: MIT License
Classifier: Operating System :: OS Independent
Requires-Python: >=3.6
